AUTHORS.rst
CONTRIBUTING.rst
HISTORY.rst
LATEST_VERSION_NOTES.rst
LICENSE
MANIFEST.in
README.rst
report_issue.py
setup.cfg
setup.py
tox.ini
docs/Makefile
docs/api.rst
docs/auths.rst
docs/conf.py
docs/decorators.rst
docs/events.rst
docs/gists.rst
docs/git.rst
docs/github.rst
docs/index.rst
docs/issues.rst
docs/models.rst
docs/notifications.rst
docs/orgs.rst
docs/project_changelog.rst
docs/pulls.rst
docs/repos.rst
docs/search_structs.rst
docs/structs.rst
docs/testing.rst
docs/users.rst
docs/examples/gist.rst
docs/examples/git.rst
docs/examples/github.rst
docs/examples/issue.rst
docs/examples/iterators.rst
docs/examples/logging.rst
docs/examples/oauth.rst
docs/examples/octocat.rst
docs/examples/two_factor_auth.rst
docs/examples/source/browser.py
docs/examples/source/logging_ex.py
docs/examples/source/octocat_say.py
docs/examples/source/wrap_text.py
github3/__about__.py
github3/__init__.py
github3/api.py
github3/auths.py
github3/decorators.py
github3/events.py
github3/exceptions.py
github3/git.py
github3/github.py
github3/licenses.py
github3/models.py
github3/notifications.py
github3/orgs.py
github3/pulls.py
github3/session.py
github3/structs.py
github3/users.py
github3/utils.py
github3/gists/__init__.py
github3/gists/comment.py
github3/gists/file.py
github3/gists/gist.py
github3/gists/history.py
github3/issues/__init__.py
github3/issues/comment.py
github3/issues/event.py
github3/issues/issue.py
github3/issues/label.py
github3/issues/milestone.py
github3/repos/__init__.py
github3/repos/branch.py
github3/repos/comment.py
github3/repos/commit.py
github3/repos/comparison.py
github3/repos/contents.py
github3/repos/deployment.py
github3/repos/hook.py
github3/repos/issue_import.py
github3/repos/pages.py
github3/repos/release.py
github3/repos/repo.py
github3/repos/stats.py
github3/repos/status.py
github3/repos/tag.py
github3/search/__init__.py
github3/search/code.py
github3/search/issue.py
github3/search/repository.py
github3/search/user.py
images/gh3-logo.png
sqre_codekit_github3.py.egg-info/PKG-INFO
sqre_codekit_github3.py.egg-info/SOURCES.txt
sqre_codekit_github3.py.egg-info/dependency_links.txt
sqre_codekit_github3.py.egg-info/requires.txt
sqre_codekit_github3.py.egg-info/top_level.txt
