Metadata-Version: 1.1
Name: sqre-codekit-github3.py
Version: 1.0.0a4
Summary: Python wrapper for the GitHub API(http://developer.github.com/v3)
Home-page: https://github3py.readthedocs.io
Author: Ian Cordasco
Author-email: graffatcolmingov@gmail.com
License: 3-clause BSD
Platform: UNKNOWN
Classifier: Development Status :: 5 - Production/Stable
Classifier: License :: OSI Approved
Classifier: License :: OSI Approved :: BSD License
Classifier: Intended Audience :: Developers
Classifier: Programming Language :: Python
Classifier: Programming Language :: Python :: 2
Classifier: Programming Language :: Python :: 2.7
Classifier: Programming Language :: Python :: 3
Classifier: Programming Language :: Python :: 3.3
Classifier: Programming Language :: Python :: 3.4
Classifier: Programming Language :: Python :: 3.5
Classifier: Programming Language :: Python :: Implementation :: CPython
